<?xml version="1.0" encoding="UTF-8" standalone="yes"?>
<word xmlns:xsi="http://www.w3.org/2001/XMLSchema-instance">
	<entry>
		<en>Would you like to buy this wallpaper?</en>
		<ko>배경을 구매하시겠습니까?</ko>
		<jp>この壁紙を購入しますか？</jp>
	</entry>
	<entry>
		<en>Would you like to buy this nest?</en>
		<ko>둥지를 구매하시겠습니까?</ko>
		<jp>この巣を購入しますか？</jp>
	</entry>
	<entry>
		<en>Are you sure you want to delete all birds?</en>
		<ko>모든 오목눈이를 삭제하시겠습니까?</ko>
		<jp>すべての鳥さんを消しますか？</jp>
	</entry>
	<entry>
		<en>You don’t have enough clovers.</en>
		<ko>클로버가 모자랍니다</ko>
		<jp>クローバーが足りません。</jp>
	</entry>
	<entry>
		<en>You don’t have enough golden clovers.</en>
		<ko>황금 클로버가 모자랍니다</ko>
		<jp>金のクローバーが足りません。</jp>
	</entry>
	<entry>
		<en>Are you sure you want to end the game?</en>
		<ko>게임을 종료하시겠습니까?</ko>
		<jp>ゲームを終了してもいいですか？</jp>
	</entry>
	<entry>
		<en>You now have enough heart point. Please hatch your egg.</en>
		<ko>필요한 호감도를 달성했어요 알을 부화시켜주세요~</ko>
		<jp>好感度がいっぱいになりました。卵を孵化してください。</jp>
	</entry>
	<entry>
		<en>Affection achievement! You can now hatch new type of egg!</en>
		<ko>호감도 달성! 새로운 알을 부화시킬 수 있어요!</ko>
		<jp>好感度を達成！新しい種類の卵を孵化できるようになったよ！</jp>
	</entry>
	<entry>
		<en>Need to collect 30 birds.</en>
		<ko>오목눈이 30마리 수집필요</ko>
		<jp>鳥を30羽集める必要がある。</jp>
	</entry>
	<entry>
		<en>Do you want to expand nest 2?</en>
		<ko>2번 둥지를 확장하시겠습니까?</ko>
		<jp>2つ目の巣を大きくしますか？</jp>
	</entry>
	<entry>
		<en>Giving life to the bird.</en>
		<ko>오목눈이에게 생명을 주고 있습니다.</ko>
		<jp>鳥さんにライフを与えてるよ。</jp>
	</entry>
	<entry>
		<en>Making bird feed.</en>
		<ko>오목눈이 먹이를 만들고 있습니다.</ko>
		<jp>鳥さんの餌を作成してるよ。</jp>
	</entry>
	<entry>
		<en>Tidy up the bird nest.</en>
		<ko>둥지를 청소하고 있습니다.</ko>
		<jp>鳥さんの巣を掃除してるよ。</jp>
	</entry>
	<entry>
		<en>Creating the environment.</en>
		<ko>자연을 생성하고 있습니다.</ko>
		<jp>環境を作成してるよ。</jp>
	</entry>
	<entry>
		<en>Please wait a moment.</en>
		<ko>잠시만 기다려 주세요.</ko>
		<jp>しばらく待ってね。</jp>
	</entry>
	<entry>
		<en>Creating data for first-time running this game.</en>
		<ko>첫 게임 실행시 데이터파일 생성중입니다.</ko>
		<jp>初回プレイのデータを作成してるよ。</jp>
	</entry>
	<entry>
		<en>Gathering the birds.</en>
		<ko>오목눈이를 불러 오는 중입니다.</ko>
		<jp>鳥さんをあつめてるよ。</jp>
	</entry>
	<entry>
		<en>Can obtain by using AR.</en>
		<ko>AR로 획득 가능</ko>
		<jp>ARで手に入ります。</jp>
	</entry>
	<entry>
		<en>Faster bird Hatching Time</en>
		<ko>오목눈이 부화 시간 단축</ko>
		<jp>鳥さんの孵化時間を短縮</jp>
	</entry>
	<entry>
		<en>Automatically feed without touch</en>
		<ko>터치없이 자동 모이 지급</ko>
		<jp>タッチせずに自動的に餌をあげる</jp>
	</entry>
	<entry>
		<en>Saved to phone gallery.</en>
		<ko>갤러리에 저장되었습니다.</ko>
		<jp>携帯ギャラリーに保存しました。</jp>
	</entry>
	<entry>
		<en>You haven’t obtained any reward yet. Do you want quit AR mode?</en>
		<ko>보상을 받지 못했습니다. AR 모드를 종료하시겠습니까?</ko>
		<jp>あなたはまだ報酬をもらっていません。 ARモードを終了しますか？</jp>
	</entry>
	<entry>
		<en>There's no more Ads for today.</en>
		<ko>오늘 광고를 다 소진하였습니다.</ko>
		<jp>本日の広告は終了しました。</jp>
	</entry>
	<entry>
		<en>If you have purchased an item in the past, press the recovery button to recover it.</en>
		<ko>상품을 구입 한 적이있는 경우 복구 버튼을 눌러 복구합니다.</ko>
		<jp>アイテムを購入したことがある場合の回復ボタンを押して回復します。</jp>
	</entry>
	<entry>
		<en>Data is not restored when deleting a game with a consumable item.</en>
		<ko>소모성 아이템으로 게임을 삭제하면 데이터가 복원되지 않습니다.</ko>
		<jp>消耗性アイテムでゲームを削除するときに、データが復元されません。</jp>
	</entry>
	<entry>
		<en>You can get it through a one-day limited ad view.</en>
		<ko>1일 한정 광고보기로 얻을 수 있습니다. </ko>
		<jp>1日限定の広告視聴でご利用いただけます。</jp>
	</entry>
	<entry>
		<en>*Growl*So hungry...</en>
		<ko>꼬르륵 배가 고파요...</ko>
		<jp>ペコペコ</jp>
	</entry>
	<entry>
		<en>The birds are waiting for food~ Let’s go give the seeds now!</en>
		<ko>오목눈이들이 먹이를 기다리고 있어요~ 얼른 씨앗을 주러가요!</ko>
		<jp>鳥たちが餌を待っています~。早く種をあげに行きましょう！</jp>
	</entry>
</word>